{"batchcomplete": "", "query": {"normalized": [{"from": "Trimble, Tennessee ", "to": "Trimble, Tennessee"}, {"from": " Troy, Tennessee ", "to": "Troy, Tennessee"}, {"from": " Tullahoma, Tennessee ", "to": "Tullahoma, Tennessee"}, {"from": " Tusculum, Tennessee ", "to": "Tusculum, Tennessee"}, {"from": " Unicoi, Tennessee ", "to": "Unicoi, Tennessee"}, {"from": " Union City, Tennessee ", "to": "Union City, Tennessee"}, {"from": " Vanleer, Tennessee ", "to": "Vanleer, Tennessee"}, {"from": " Viola, Tennessee ", "to": "Viola, Tennessee"}, {"from": " Vonore, Tennessee ", "to": "Vonore, Tennessee"}, {"from": " Walden, Tennessee ", "to": "Walden, Tennessee"}, {"from": " Wartburg, Tennessee ", "to": "Wartburg, Tennessee"}, {"from": " Wartrace, Tennessee ", "to": "Wartrace, Tennessee"}, {"from": " Watauga, Tennessee ", "to": "Watauga, Tennessee"}, {"from": " Watertown, Tennessee ", "to": "Watertown, Tennessee"}, {"from": " Waverly, Tennessee ", "to": "Waverly, Tennessee"}, {"from": " Waynesboro, Tennessee ", "to": "Waynesboro, Tennessee"}, {"from": " Westmoreland, Tennessee ", "to": "Westmoreland, Tennessee"}, {"from": " White Bluff, Tennessee ", "to": "White Bluff, Tennessee"}, {"from": " White House, Tennessee ", "to": "White House, Tennessee"}, {"from": " White Pine, Tennessee ", "to": "White Pine, Tennessee"}, {"from": " Whiteville, Tennessee ", "to": "Whiteville, Tennessee"}, {"from": " Whitwell, Tennessee ", "to": "Whitwell, Tennessee"}, {"from": " Williston, Tennessee ", "to": "Williston, Tennessee"}, {"from": " Winchester, Tennessee ", "to": "Winchester, Tennessee"}, {"from": " Winfield, Tennessee ", "to": "Winfield, Tennessee"}, {"from": " Woodbury, Tennessee ", "to": "Woodbury, Tennessee"}, {"from": " Woodland Mills, Tennessee ", "to": "Woodland Mills, Tennessee"}, {"from": " Yorkville, Tennessee ", "to": "Yorkville, Tennessee"}, {"from": " Houston, Texas ", "to": "Houston, Texas"}, {"from": " San Antonio, Texas ", "to": "San Antonio, Texas"}, {"from": " Dallas, Texas ", "to": "Dallas, Texas"}, {"from": " Austin, Texas ", "to": "Austin, Texas"}, {"from": " Fort Worth, Texas ", "to": "Fort Worth, Texas"}, {"from": " El Paso, Texas ", "to": "El Paso, Texas"}, {"from": " Arlington, Texas ", "to": "Arlington, Texas"}, {"from": " Corpus Christi, Texas ", "to": "Corpus Christi, Texas"}, {"from": " Plano, Texas ", "to": "Plano, Texas"}, {"from": " Lubbock, Texas ", "to": "Lubbock, Texas"}, {"from": " Laredo, Texas ", "to": "Laredo, Texas"}, {"from": " Irving, Texas ", "to": "Irving, Texas"}, {"from": " Garland, Texas ", "to": "Garland, Texas"}, {"from": " Frisco, Texas ", "to": "Frisco, Texas"}, {"from": " McKinney, Texas ", "to": "McKinney, Texas"}, {"from": " Grand Prairie, Texas ", "to": "Grand Prairie, Texas"}, {"from": " Amarillo, Texas ", "to": "Amarillo, Texas"}, {"from": " Brownsville, Texas ", "to": "Brownsville, Texas"}, {"from": " Killeen, Texas ", "to": "Killeen, Texas"}, {"from": " Denton, Texas ", "to": "Denton, Texas"}, {"from": " Mesquite, Texas ", "to": "Mesquite, Texas"}, {"from": " Pasadena, Texas", "to": "Pasadena, Texas"}], "pages": {"151232": {"pageid": 151232, "ns": 0, "title": "Amarillo, Texas", "contentmodel": "wikitext", "pagelanguage": "en", "pagelanguagehtmlcode": "en", "pagelanguagedir": "ltr", "touched": "2023-10-15T01:19:37Z", "lastrevid": 1180185437, "length": 113652}, "95815": {"pageid": 95815, "ns": 0, "title": "Arlington, Texas", "contentmodel": "wikitext", "pagelanguage": "en", "pagelanguagehtmlcode": "en", "pagelanguagedir": "ltr", "touched": "2023-10-12T23:59:09Z", "lastrevid": 1179869484, "length": 78541}, "1998": {"pageid": 1998, "ns": 0, "title": "Austin, Texas", "contentmodel": "wikitext", "pagelanguage": "en", "pagelanguagehtmlcode": "en", "pagelanguagedir": "ltr", "touched": "2023-10-15T19:27:02Z", "lastrevid": 1180300678, "length": 225892}, "135600": {"pageid": 135600, "ns": 0, "title": "Brownsville, Texas", "contentmodel": "wikitext", "pagelanguage": "en", "pagelanguagehtmlcode": "en", "pagelanguagedir": "ltr", "touched": "2023-10-10T22:36:00Z", "lastrevid": 1177899822, "length": 163119}, "151217": {"pageid": 151217, "ns": 0, "title": "Corpus Christi, Texas", "contentmodel": "wikitext", "pagelanguage": "en", "pagelanguagehtmlcode": "en", "pagelanguagedir": "ltr", "touched": "2023-10-16T05:43:59Z", "lastrevid": 1180368809, "length": 77056}, "21912865": {"pageid": 21912865, "ns": 0, "title": "Dallas, Texas", "contentmodel": "wikitext", "pagelanguage": "en", "pagelanguagehtmlcode": "en", "pagelanguagedir": "ltr", "touched": "2023-10-11T16:51:48Z", "lastrevid": 1157000456, "length": 77, "redirect": ""}, "135768": {"pageid": 135768, "ns": 0, "title": "Denton, Texas", "contentmodel": "wikitext", "pagelanguage": "en", "pagelanguagehtmlcode": "en", "pagelanguagedir": "ltr", "touched": "2023-10-15T16:37:40Z", "lastrevid": 1178307373, "length": 81670}, "135823": {"pageid": 135823, "ns": 0, "title": "El Paso, Texas", "contentmodel": "wikitext", "pagelanguage": "en", "pagelanguagehtmlcode": "en", "pagelanguagedir": "ltr", "touched": "2023-10-15T23:18:53Z", "lastrevid": 1180219950, "length": 176101}, "53839": {"pageid": 53839, "ns": 0, "title": "Fort Worth, Texas", "contentmodel": "wikitext", "pagelanguage": "en", "pagelanguagehtmlcode": "en", "pagelanguagedir": "ltr", "touched": "2023-10-15T16:37:38Z", "lastrevid": 1179594293, "length": 148315}, "151137": {"pageid": 151137, "ns": 0, "title": "Frisco, Texas", "contentmodel": "wikitext", "pagelanguage": "en", "pagelanguagehtmlcode": "en", "pagelanguagedir": "ltr", "touched": "2023-10-13T10:22:08Z", "lastrevid": 1179927066, "length": 42760}, "151138": {"pageid": 151138, "ns": 0, "title": "Garland, Texas", "contentmodel": "wikitext", "pagelanguage": "en", "pagelanguagehtmlcode": "en", "pagelanguagedir": "ltr", "touched": "2023-10-13T06:56:56Z", "lastrevid": 1172111453, "length": 54506}, "151157": {"pageid": 151157, "ns": 0, "title": "Grand Prairie, Texas", "contentmodel": "wikitext", "pagelanguage": "en", "pagelanguagehtmlcode": "en", "pagelanguagedir": "ltr", "touched": "2023-10-10T22:36:08Z", "lastrevid": 1176654384, "length": 40364}, "19944876": {"pageid": 19944876, "ns": 0, "title": "Houston, Texas", "contentmodel": "wikitext", "pagelanguage": "en", "pagelanguagehtmlcode": "en", "pagelanguagedir": "ltr", "touched": "2023-10-11T16:14:46Z", "lastrevid": 1142388929, "length": 65, "redirect": ""}, "135752": {"pageid": 135752, "ns": 0, "title": "Irving, Texas", "contentmodel": "wikitext", "pagelanguage": "en", "pagelanguagehtmlcode": "en", "pagelanguagedir": "ltr", "touched": "2023-10-10T22:36:00Z", "lastrevid": 1178399094, "length": 58673}, "135478": {"pageid": 135478, "ns": 0, "title": "Killeen, Texas", "contentmodel": "wikitext", "pagelanguage": "en", "pagelanguagehtmlcode": "en", "pagelanguagedir": "ltr", "touched": "2023-10-16T15:55:57Z", "lastrevid": 1180427527, "length": 41463}, "136773": {"pageid": 136773, "ns": 0, "title": "Laredo, Texas", "contentmodel": "wikitext", "pagelanguage": "en", "pagelanguagehtmlcode": "en", "pagelanguagedir": "ltr", "touched": "2023-10-15T23:18:53Z", "lastrevid": 1179559362, "length": 145334}, "136320": {"pageid": 136320, "ns": 0, "title": "Lubbock, Texas", "contentmodel": "wikitext", "pagelanguage": "en", "pagelanguagehtmlcode": "en", "pagelanguagedir": "ltr", "touched": "2023-10-13T06:56:56Z", "lastrevid": 1179393716, "length": 125908}, "135698": {"pageid": 135698, "ns": 0, "title": "McKinney, Texas", "contentmodel": "wikitext", "pagelanguage": "en", "pagelanguagehtmlcode": "en", "pagelanguagedir": "ltr", "touched": "2023-10-10T22:36:00Z", "lastrevid": 1179185768, "length": 38353}, "151160": {"pageid": 151160, "ns": 0, "title": "Mesquite, Texas", "contentmodel": "wikitext", "pagelanguage": "en", "pagelanguagehtmlcode": "en", "pagelanguagedir": "ltr", "touched": "2023-10-13T06:56:56Z", "lastrevid": 1178408918, "length": 43042}, "136015": {"pageid": 136015, "ns": 0, "title": "Pasadena, Texas", "contentmodel": "wikitext", "pagelanguage": "en", "pagelanguagehtmlcode": "en", "pagelanguagedir": "ltr", "touched": "2023-10-10T22:36:00Z", "lastrevid": 1177704146, "length": 41185}, "151140": {"pageid": 151140, "ns": 0, "title": "Plano, Texas", "contentmodel": "wikitext", "pagelanguage": "en", "pagelanguagehtmlcode": "en", "pagelanguagedir": "ltr", "touched": "2023-10-13T06:56:56Z", "lastrevid": 1178683823, "length": 87893}, "20863320": {"pageid": 20863320, "ns": 0, "title": "San Antonio, Texas", "contentmodel": "wikitext", "pagelanguage": "en", "pagelanguagehtmlcode": "en", "pagelanguagedir": "ltr", "touched": "2023-10-12T17:30:06Z", "lastrevid": 1129029014, "length": 98, "redirect": ""}, "151073": {"pageid": 151073, "ns": 0, "title": "Trimble, Tennessee", "contentmodel": "wikitext", "pagelanguage": "en", "pagelanguagehtmlcode": "en", "pagelanguagedir": "ltr", "touched": "2023-10-10T22:36:08Z", "lastrevid": 1166331630, "length": 8513}, "135317": {"pageid": 135317, "ns": 0, "title": "Troy, Tennessee", "contentmodel": "wikitext", "pagelanguage": "en", "pagelanguagehtmlcode": "en", "pagelanguagedir": "ltr", "touched": "2023-10-10T22:36:00Z", "lastrevid": 1166331676, "length": 9752}, "151067": {"pageid": 151067, "ns": 0, "title": "Tullahoma, Tennessee", "contentmodel": "wikitext", "pagelanguage": "en", "pagelanguagehtmlcode": "en", "pagelanguagedir": "ltr", "touched": "2023-10-10T22:36:08Z", "lastrevid": 1177338193, "length": 32716}, "135197": {"pageid": 135197, "ns": 0, "title": "Tusculum, Tennessee", "contentmodel": "wikitext", "pagelanguage": "en", "pagelanguagehtmlcode": "en", "pagelanguagedir": "ltr", "touched": "2023-10-10T22:36:00Z", "lastrevid": 1169541405, "length": 10994}, "135397": {"pageid": 135397, "ns": 0, "title": "Unicoi, Tennessee", "contentmodel": "wikitext", "pagelanguage": "en", "pagelanguagehtmlcode": "en", "pagelanguagedir": "ltr", "touched": "2023-10-10T22:36:00Z", "lastrevid": 1166331850, "length": 12958}, "135318": {"pageid": 135318, "ns": 0, "title": "Union City, Tennessee", "contentmodel": "wikitext", "pagelanguage": "en", "pagelanguagehtmlcode": "en", "pagelanguagedir": "ltr", "touched": "2023-10-10T22:36:00Z", "lastrevid": 1177982077, "length": 17703}, "135156": {"pageid": 135156, "ns": 0, "title": "Vanleer, Tennessee", "contentmodel": "wikitext", "pagelanguage": "en", "pagelanguagehtmlcode": "en", "pagelanguagedir": "ltr", "touched": "2023-10-10T22:36:00Z", "lastrevid": 1166332060, "length": 8778}, "135405": {"pageid": 135405, "ns": 0, "title": "Viola, Tennessee", "contentmodel": "wikitext", "pagelanguage": "en", "pagelanguagehtmlcode": "en", "pagelanguagedir": "ltr", "touched": "2023-10-10T22:36:00Z", "lastrevid": 1166332254, "length": 10636}, "151058": {"pageid": 151058, "ns": 0, "title": "Vonore, Tennessee", "contentmodel": "wikitext", "pagelanguage": "en", "pagelanguagehtmlcode": "en", "pagelanguagedir": "ltr", "touched": "2023-10-10T22:36:08Z", "lastrevid": 1175676969, "length": 19028}, "135218": {"pageid": 135218, "ns": 0, "title": "Walden, Tennessee", "contentmodel": "wikitext", "pagelanguage": "en", "pagelanguagehtmlcode": "en", "pagelanguagedir": "ltr", "touched": "2023-10-10T22:36:00Z", "lastrevid": 1117001223, "length": 9506}, "135310": {"pageid": 135310, "ns": 0, "title": "Wartburg, Tennessee", "contentmodel": "wikitext", "pagelanguage": "en", "pagelanguagehtmlcode": "en", "pagelanguagedir": "ltr", "touched": "2023-10-10T22:36:00Z", "lastrevid": 1165906666, "length": 15436}, "135079": {"pageid": 135079, "ns": 0, "title": "Wartrace, Tennessee", "contentmodel": "wikitext", "pagelanguage": "en", "pagelanguagehtmlcode": "en", "pagelanguagedir": "ltr", "touched": "2023-10-10T22:36:00Z", "lastrevid": 1171052995, "length": 14302}, "151062": {"pageid": 151062, "ns": 0, "title": "Watauga, Tennessee", "contentmodel": "wikitext", "pagelanguage": "en", "pagelanguagehtmlcode": "en", "pagelanguagedir": "ltr", "touched": "2023-10-10T22:36:08Z", "lastrevid": 1165906743, "length": 11514}, "135429": {"pageid": 135429, "ns": 0, "title": "Watertown, Tennessee", "contentmodel": "wikitext", "pagelanguage": "en", "pagelanguagehtmlcode": "en", "pagelanguagedir": "ltr", "touched": "2023-10-10T22:36:00Z", "lastrevid": 1179147146, "length": 13288}, "135248": {"pageid": 135248, "ns": 0, "title": "Waverly, Tennessee", "contentmodel": "wikitext", "pagelanguage": "en", "pagelanguagehtmlcode": "en", "pagelanguagedir": "ltr", "touched": "2023-10-10T22:36:00Z", "lastrevid": 1144884093, "length": 15641}, "135412": {"pageid": 135412, "ns": 0, "title": "Waynesboro, Tennessee", "contentmodel": "wikitext", "pagelanguage": "en", "pagelanguagehtmlcode": "en", "pagelanguagedir": "ltr", "touched": "2023-10-10T22:36:00Z", "lastrevid": 1165906913, "length": 15593}, "135384": {"pageid": 135384, "ns": 0, "title": "Westmoreland, Tennessee", "contentmodel": "wikitext", "pagelanguage": "en", "pagelanguagehtmlcode": "en", "pagelanguagedir": "ltr", "touched": "2023-10-10T22:36:00Z", "lastrevid": 1173396105, "length": 10257}, "135157": {"pageid": 135157, "ns": 0, "title": "White Bluff, Tennessee", "contentmodel": "wikitext", "pagelanguage": "en", "pagelanguagehtmlcode": "en", "pagelanguagedir": "ltr", "touched": "2023-10-10T22:36:00Z", "lastrevid": 1166333458, "length": 12013}, "151099": {"pageid": 151099, "ns": 0, "title": "White House, Tennessee", "contentmodel": "wikitext", "pagelanguage": "en", "pagelanguagehtmlcode": "en", "pagelanguagedir": "ltr", "touched": "2023-10-10T22:36:08Z", "lastrevid": 1176149079, "length": 17267}, "151084": {"pageid": 151084, "ns": 0, "title": "White Pine, Tennessee", "contentmodel": "wikitext", "pagelanguage": "en", "pagelanguagehtmlcode": "en", "pagelanguagedir": "ltr", "touched": "2023-10-10T22:36:08Z", "lastrevid": 1166333482, "length": 17723}, "135226": {"pageid": 135226, "ns": 0, "title": "Whiteville, Tennessee", "contentmodel": "wikitext", "pagelanguage": "en", "pagelanguagehtmlcode": "en", "pagelanguagedir": "ltr", "touched": "2023-10-10T22:36:00Z", "lastrevid": 1169784281, "length": 11232}, "135285": {"pageid": 135285, "ns": 0, "title": "Whitwell, Tennessee", "contentmodel": "wikitext", "pagelanguage": "en", "pagelanguagehtmlcode": "en", "pagelanguagedir": "ltr", "touched": "2023-10-10T22:36:00Z", "lastrevid": 1165907574, "length": 13867}, "135171": {"pageid": 135171, "ns": 0, "title": "Williston, Tennessee", "contentmodel": "wikitext", "pagelanguage": "en", "pagelanguagehtmlcode": "en", "pagelanguagedir": "ltr", "touched": "2023-10-10T22:36:00Z", "lastrevid": 1165907788, "length": 8396}, "135179": {"pageid": 135179, "ns": 0, "title": "Winchester, Tennessee", "contentmodel": "wikitext", "pagelanguage": "en", "pagelanguagehtmlcode": "en", "pagelanguagedir": "ltr", "touched": "2023-10-10T22:36:00Z", "lastrevid": 1171350157, "length": 16816}, "135355": {"pageid": 135355, "ns": 0, "title": "Winfield, Tennessee", "contentmodel": "wikitext", "pagelanguage": "en", "pagelanguagehtmlcode": "en", "pagelanguagedir": "ltr", "touched": "2023-10-10T22:36:00Z", "lastrevid": 1166334066, "length": 8967}, "135103": {"pageid": 135103, "ns": 0, "title": "Woodbury, Tennessee", "contentmodel": "wikitext", "pagelanguage": "en", "pagelanguagehtmlcode": "en", "pagelanguagedir": "ltr", "touched": "2023-10-10T22:36:00Z", "lastrevid": 1166334257, "length": 15527}, "135319": {"pageid": 135319, "ns": 0, "title": "Woodland Mills, Tennessee", "contentmodel": "wikitext", "pagelanguage": "en", "pagelanguagehtmlcode": "en", "pagelanguagedir": "ltr", "touched": "2023-10-10T22:36:00Z", "lastrevid": 1165908368, "length": 7841}, "135187": {"pageid": 135187, "ns": 0, "title": "Yorkville, Tennessee", "contentmodel": "wikitext", "pagelanguage": "en", "pagelanguagehtmlcode": "en", "pagelanguagedir": "ltr", "touched": "2023-10-10T22:36:00Z", "lastrevid": 1165908654, "length": 8583}}}}