{"batchcomplete": "", "query": {"normalized": [{"from": "Bostwick, Georgia ", "to": "Bostwick, Georgia"}, {"from": " Bowdon, Georgia ", "to": "Bowdon, Georgia"}, {"from": " Bowersville, Georgia ", "to": "Bowersville, Georgia"}, {"from": " Bowman, Georgia ", "to": "Bowman, Georgia"}, {"from": " Braselton, Georgia ", "to": "Braselton, Georgia"}, {"from": " Braswell, Georgia ", "to": "Braswell, Georgia"}, {"from": " Bremen, Georgia ", "to": "Bremen, Georgia"}, {"from": " Brinson, Georgia ", "to": "Brinson, Georgia"}, {"from": " Bronwood, Georgia ", "to": "Bronwood, Georgia"}, {"from": " Brookhaven, Georgia ", "to": "Brookhaven, Georgia"}, {"from": " Brooklet, Georgia ", "to": "Brooklet, Georgia"}, {"from": " Brooks, Georgia ", "to": "Brooks, Georgia"}, {"from": " Broxton, Georgia ", "to": "Broxton, Georgia"}, {"from": " Brunswick, Georgia ", "to": "Brunswick, Georgia"}, {"from": " Buchanan, Georgia ", "to": "Buchanan, Georgia"}, {"from": " Buckhead, Morgan County, Georgia ", "to": "Buckhead, Morgan County, Georgia"}, {"from": " Buena Vista, Georgia ", "to": "Buena Vista, Georgia"}, {"from": " Buford, Georgia ", "to": "Buford, Georgia"}, {"from": " Butler, Georgia ", "to": "Butler, Georgia"}, {"from": " Byromville, Georgia ", "to": "Byromville, Georgia"}, {"from": " Byron, Georgia ", "to": "Byron, Georgia"}, {"from": " Cadwell, Georgia ", "to": "Cadwell, Georgia"}, {"from": " Cairo, Georgia ", "to": "Cairo, Georgia"}, {"from": " Calhoun, Georgia ", "to": "Calhoun, Georgia"}, {"from": " Camak, Georgia ", "to": "Camak, Georgia"}, {"from": " Camilla, Georgia ", "to": "Camilla, Georgia"}, {"from": " Canon, Georgia ", "to": "Canon, Georgia"}, {"from": " Canton, Georgia ", "to": "Canton, Georgia"}, {"from": " Carl, Georgia ", "to": "Carl, Georgia"}, {"from": " Carlton, Georgia ", "to": "Carlton, Georgia"}, {"from": " Carnesville, Georgia ", "to": "Carnesville, Georgia"}, {"from": " Carrollton, Georgia ", "to": "Carrollton, Georgia"}, {"from": " Cartersville, Georgia ", "to": "Cartersville, Georgia"}, {"from": " Cave Spring, Georgia ", "to": "Cave Spring, Georgia"}, {"from": " Cecil, Georgia ", "to": "Cecil, Georgia"}, {"from": " Cedartown, Georgia ", "to": "Cedartown, Georgia"}, {"from": " Centerville, Georgia ", "to": "Centerville, Georgia"}, {"from": " Centralhatchee, Georgia ", "to": "Centralhatchee, Georgia"}, {"from": " Chamblee, Georgia ", "to": "Chamblee, Georgia"}, {"from": " Chatsworth, Georgia ", "to": "Chatsworth, Georgia"}, {"from": " Chattahoochee Hills, Georgia ", "to": "Chattahoochee Hills, Georgia"}, {"from": " Chauncey, Georgia ", "to": "Chauncey, Georgia"}, {"from": " Chester, Georgia ", "to": "Chester, Georgia"}, {"from": " Chickamauga, Georgia ", "to": "Chickamauga, Georgia"}, {"from": " Clarkesville, Georgia ", "to": "Clarkesville, Georgia"}, {"from": " Clarkston, Georgia ", "to": "Clarkston, Georgia"}, {"from": " Claxton, Georgia ", "to": "Claxton, Georgia"}, {"from": " Clayton, Georgia ", "to": "Clayton, Georgia"}, {"from": " Clermont, Georgia ", "to": "Clermont, Georgia"}, {"from": " Cleveland, Georgia", "to": "Cleveland, Georgia"}], "pages": {"110273": {"pageid": 110273, "ns": 0, "title": "Bostwick, Georgia", "contentmodel": "wikitext", "pagelanguage": "en", "pagelanguagehtmlcode": "en", "pagelanguagedir": "ltr", "touched": "2023-10-10T22:35:41Z", "lastrevid": 1166016026, "length": 10036}, "109924": {"pageid": 109924, "ns": 0, "title": "Bowdon, Georgia", "contentmodel": "wikitext", "pagelanguage": "en", "pagelanguagehtmlcode": "en", "pagelanguagedir": "ltr", "touched": "2023-10-10T22:35:40Z", "lastrevid": 1176253533, "length": 15160}, "110169": {"pageid": 110169, "ns": 0, "title": "Bowersville, Georgia", "contentmodel": "wikitext", "pagelanguage": "en", "pagelanguagehtmlcode": "en", "pagelanguagedir": "ltr", "touched": "2023-10-10T22:35:40Z", "lastrevid": 1166016079, "length": 9531}, "110072": {"pageid": 110072, "ns": 0, "title": "Bowman, Georgia", "contentmodel": "wikitext", "pagelanguage": "en", "pagelanguagehtmlcode": "en", "pagelanguagedir": "ltr", "touched": "2023-10-10T22:35:40Z", "lastrevid": 1165536752, "length": 11416}, "109872": {"pageid": 109872, "ns": 0, "title": "Braselton, Georgia", "contentmodel": "wikitext", "pagelanguage": "en", "pagelanguagehtmlcode": "en", "pagelanguagedir": "ltr", "touched": "2023-10-10T22:35:40Z", "lastrevid": 1177440193, "length": 18145}, "110295": {"pageid": 110295, "ns": 0, "title": "Braswell, Georgia", "contentmodel": "wikitext", "pagelanguage": "en", "pagelanguagehtmlcode": "en", "pagelanguagedir": "ltr", "touched": "2023-10-10T22:35:41Z", "lastrevid": 1165536888, "length": 10561}, "109925": {"pageid": 109925, "ns": 0, "title": "Bremen, Georgia", "contentmodel": "wikitext", "pagelanguage": "en", "pagelanguagehtmlcode": "en", "pagelanguagedir": "ltr", "touched": "2023-10-10T22:35:40Z", "lastrevid": 1172047395, "length": 26900}, "110029": {"pageid": 110029, "ns": 0, "title": "Brinson, Georgia", "contentmodel": "wikitext", "pagelanguage": "en", "pagelanguagehtmlcode": "en", "pagelanguagedir": "ltr", "touched": "2023-10-10T22:35:40Z", "lastrevid": 1178991856, "length": 10554}, "110368": {"pageid": 110368, "ns": 0, "title": "Bronwood, Georgia", "contentmodel": "wikitext", "pagelanguage": "en", "pagelanguagehtmlcode": "en", "pagelanguagedir": "ltr", "touched": "2023-10-10T22:35:41Z", "lastrevid": 1166016399, "length": 11459}, "2321072": {"pageid": 2321072, "ns": 0, "title": "Brookhaven, Georgia", "contentmodel": "wikitext", "pagelanguage": "en", "pagelanguagehtmlcode": "en", "pagelanguagedir": "ltr", "touched": "2023-10-10T22:41:30Z", "lastrevid": 1172028453, "length": 51133}, "109900": {"pageid": 109900, "ns": 0, "title": "Brooklet, Georgia", "contentmodel": "wikitext", "pagelanguage": "en", "pagelanguagehtmlcode": "en", "pagelanguagedir": "ltr", "touched": "2023-10-10T22:35:40Z", "lastrevid": 1168590125, "length": 17895}, "110089": {"pageid": 110089, "ns": 0, "title": "Brooks, Georgia", "contentmodel": "wikitext", "pagelanguage": "en", "pagelanguagehtmlcode": "en", "pagelanguagedir": "ltr", "touched": "2023-10-10T22:35:40Z", "lastrevid": 1166016476, "length": 12469}, "109993": {"pageid": 109993, "ns": 0, "title": "Broxton, Georgia", "contentmodel": "wikitext", "pagelanguage": "en", "pagelanguagehtmlcode": "en", "pagelanguagedir": "ltr", "touched": "2023-10-10T22:35:40Z", "lastrevid": 1165537449, "length": 12752}, "110120": {"pageid": 110120, "ns": 0, "title": "Brunswick, Georgia", "contentmodel": "wikitext", "pagelanguage": "en", "pagelanguagehtmlcode": "en", "pagelanguagedir": "ltr", "touched": "2023-10-10T22:35:40Z", "lastrevid": 1179019149, "length": 115636}, "110161": {"pageid": 110161, "ns": 0, "title": "Buchanan, Georgia", "contentmodel": "wikitext", "pagelanguage": "en", "pagelanguagehtmlcode": "en", "pagelanguagedir": "ltr", "touched": "2023-10-10T22:35:40Z", "lastrevid": 1169732429, "length": 12993}, "110274": {"pageid": 110274, "ns": 0, "title": "Buckhead, Morgan County, Georgia", "contentmodel": "wikitext", "pagelanguage": "en", "pagelanguagehtmlcode": "en", "pagelanguagedir": "ltr", "touched": "2023-10-10T22:35:41Z", "lastrevid": 1176980893, "length": 9936}, "110246": {"pageid": 110246, "ns": 0, "title": "Buena Vista, Georgia", "contentmodel": "wikitext", "pagelanguage": "en", "pagelanguagehtmlcode": "en", "pagelanguagedir": "ltr", "touched": "2023-10-10T22:35:41Z", "lastrevid": 1167065988, "length": 16589}, "110137": {"pageid": 110137, "ns": 0, "title": "Buford, Georgia", "contentmodel": "wikitext", "pagelanguage": "en", "pagelanguagehtmlcode": "en", "pagelanguagedir": "ltr", "touched": "2023-10-10T22:35:40Z", "lastrevid": 1171494776, "length": 60296}, "110361": {"pageid": 110361, "ns": 0, "title": "Butler, Georgia", "contentmodel": "wikitext", "pagelanguage": "en", "pagelanguagehtmlcode": "en", "pagelanguagedir": "ltr", "touched": "2023-10-10T22:35:41Z", "lastrevid": 1165537809, "length": 15189}, "110056": {"pageid": 110056, "ns": 0, "title": "Byromville, Georgia", "contentmodel": "wikitext", "pagelanguage": "en", "pagelanguagehtmlcode": "en", "pagelanguagedir": "ltr", "touched": "2023-10-10T22:35:40Z", "lastrevid": 1166016929, "length": 12332}, "110298": {"pageid": 110298, "ns": 0, "title": "Byron, Georgia", "contentmodel": "wikitext", "pagelanguage": "en", "pagelanguagehtmlcode": "en", "pagelanguagedir": "ltr", "touched": "2023-10-10T22:35:41Z", "lastrevid": 1165537858, "length": 15031}, "110210": {"pageid": 110210, "ns": 0, "title": "Cadwell, Georgia", "contentmodel": "wikitext", "pagelanguage": "en", "pagelanguagehtmlcode": "en", "pagelanguagedir": "ltr", "touched": "2023-10-10T22:35:40Z", "lastrevid": 1166016976, "length": 10756}, "110129": {"pageid": 110129, "ns": 0, "title": "Cairo, Georgia", "contentmodel": "wikitext", "pagelanguage": "en", "pagelanguagehtmlcode": "en", "pagelanguagedir": "ltr", "touched": "2023-10-10T22:35:40Z", "lastrevid": 1175371412, "length": 20923}, "110124": {"pageid": 110124, "ns": 0, "title": "Calhoun, Georgia", "contentmodel": "wikitext", "pagelanguage": "en", "pagelanguagehtmlcode": "en", "pagelanguagedir": "ltr", "touched": "2023-10-10T22:35:40Z", "lastrevid": 1173382154, "length": 24146}, "110417": {"pageid": 110417, "ns": 0, "title": "Camak, Georgia", "contentmodel": "wikitext", "pagelanguage": "en", "pagelanguagehtmlcode": "en", "pagelanguagedir": "ltr", "touched": "2023-10-10T22:35:41Z", "lastrevid": 1166017032, "length": 11411}, "110260": {"pageid": 110260, "ns": 0, "title": "Camilla, Georgia", "contentmodel": "wikitext", "pagelanguage": "en", "pagelanguagehtmlcode": "en", "pagelanguagedir": "ltr", "touched": "2023-10-10T22:35:41Z", "lastrevid": 1151999628, "length": 25826}, "110100": {"pageid": 110100, "ns": 0, "title": "Canon, Georgia", "contentmodel": "wikitext", "pagelanguage": "en", "pagelanguagehtmlcode": "en", "pagelanguagedir": "ltr", "touched": "2023-10-10T22:35:40Z", "lastrevid": 1165538201, "length": 11143}, "109958": {"pageid": 109958, "ns": 0, "title": "Canton, Georgia", "contentmodel": "wikitext", "pagelanguage": "en", "pagelanguagehtmlcode": "en", "pagelanguagedir": "ltr", "touched": "2023-10-10T22:35:40Z", "lastrevid": 1178343197, "length": 25348}, "109873": {"pageid": 109873, "ns": 0, "title": "Carl, Georgia", "contentmodel": "wikitext", "pagelanguage": "en", "pagelanguagehtmlcode": "en", "pagelanguagedir": "ltr", "touched": "2023-10-10T22:35:40Z", "lastrevid": 1166017271, "length": 9670}, "110240": {"pageid": 110240, "ns": 0, "title": "Carlton, Georgia", "contentmodel": "wikitext", "pagelanguage": "en", "pagelanguagehtmlcode": "en", "pagelanguagedir": "ltr", "touched": "2023-10-10T22:35:40Z", "lastrevid": 1165538360, "length": 10070}, "110101": {"pageid": 110101, "ns": 0, "title": "Carnesville, Georgia", "contentmodel": "wikitext", "pagelanguage": "en", "pagelanguagehtmlcode": "en", "pagelanguagedir": "ltr", "touched": "2023-10-13T06:26:06Z", "lastrevid": 1179907600, "length": 17332}, "109926": {"pageid": 109926, "ns": 0, "title": "Carrollton, Georgia", "contentmodel": "wikitext", "pagelanguage": "en", "pagelanguagehtmlcode": "en", "pagelanguagedir": "ltr", "touched": "2023-10-10T22:35:40Z", "lastrevid": 1175271085, "length": 41782}, "22408032": {"pageid": 22408032, "ns": 0, "title": "Cartersville, Georgia", "contentmodel": "wikitext", "pagelanguage": "en", "pagelanguagehtmlcode": "en", "pagelanguagedir": "ltr", "touched": "2023-10-10T23:01:22Z", "lastrevid": 1173978227, "length": 31618}, "110094": {"pageid": 110094, "ns": 0, "title": "Cave Spring, Georgia", "contentmodel": "wikitext", "pagelanguage": "en", "pagelanguagehtmlcode": "en", "pagelanguagedir": "ltr", "touched": "2023-10-10T22:35:40Z", "lastrevid": 1165538653, "length": 16837}, "110009": {"pageid": 110009, "ns": 0, "title": "Cecil, Georgia", "contentmodel": "wikitext", "pagelanguage": "en", "pagelanguagehtmlcode": "en", "pagelanguagedir": "ltr", "touched": "2023-10-10T22:35:40Z", "lastrevid": 1166017483, "length": 10759}, "110313": {"pageid": 110313, "ns": 0, "title": "Cedartown, Georgia", "contentmodel": "wikitext", "pagelanguage": "en", "pagelanguagehtmlcode": "en", "pagelanguagedir": "ltr", "touched": "2023-10-10T22:35:41Z", "lastrevid": 1176105072, "length": 24775}, "110180": {"pageid": 110180, "ns": 0, "title": "Centerville, Georgia", "contentmodel": "wikitext", "pagelanguage": "en", "pagelanguagehtmlcode": "en", "pagelanguagedir": "ltr", "touched": "2023-10-10T22:35:40Z", "lastrevid": 1165538828, "length": 17105}, "110172": {"pageid": 110172, "ns": 0, "title": "Centralhatchee, Georgia", "contentmodel": "wikitext", "pagelanguage": "en", "pagelanguagehtmlcode": "en", "pagelanguagedir": "ltr", "touched": "2023-10-10T22:35:40Z", "lastrevid": 1166017585, "length": 10508}, "110034": {"pageid": 110034, "ns": 0, "title": "Chamblee, Georgia", "contentmodel": "wikitext", "pagelanguage": "en", "pagelanguagehtmlcode": "en", "pagelanguagedir": "ltr", "touched": "2023-10-10T22:35:40Z", "lastrevid": 1175829049, "length": 38327}, "110277": {"pageid": 110277, "ns": 0, "title": "Chatsworth, Georgia", "contentmodel": "wikitext", "pagelanguage": "en", "pagelanguagehtmlcode": "en", "pagelanguagedir": "ltr", "touched": "2023-10-10T22:35:41Z", "lastrevid": 1168613945, "length": 14215}, "5440070": {"pageid": 5440070, "ns": 0, "title": "Chattahoochee Hills, Georgia", "contentmodel": "wikitext", "pagelanguage": "en", "pagelanguagehtmlcode": "en", "pagelanguagedir": "ltr", "touched": "2023-10-10T22:46:00Z", "lastrevid": 1173170223, "length": 11850}, "110051": {"pageid": 110051, "ns": 0, "title": "Chauncey, Georgia", "contentmodel": "wikitext", "pagelanguage": "en", "pagelanguagehtmlcode": "en", "pagelanguagedir": "ltr", "touched": "2023-10-10T22:35:40Z", "lastrevid": 1165539066, "length": 10799}, "110052": {"pageid": 110052, "ns": 0, "title": "Chester, Georgia", "contentmodel": "wikitext", "pagelanguage": "en", "pagelanguagehtmlcode": "en", "pagelanguagedir": "ltr", "touched": "2023-10-10T22:35:40Z", "lastrevid": 1166017785, "length": 10886}, "110405": {"pageid": 110405, "ns": 0, "title": "Chickamauga, Georgia", "contentmodel": "wikitext", "pagelanguage": "en", "pagelanguagehtmlcode": "en", "pagelanguagedir": "ltr", "touched": "2023-10-10T22:35:41Z", "lastrevid": 1177846925, "length": 24192}, "110150": {"pageid": 110150, "ns": 0, "title": "Clarkesville, Georgia", "contentmodel": "wikitext", "pagelanguage": "en", "pagelanguagehtmlcode": "en", "pagelanguagedir": "ltr", "touched": "2023-10-10T22:35:40Z", "lastrevid": 1175908235, "length": 18330}, "110035": {"pageid": 110035, "ns": 0, "title": "Clarkston, Georgia", "contentmodel": "wikitext", "pagelanguage": "en", "pagelanguagehtmlcode": "en", "pagelanguagedir": "ltr", "touched": "2023-10-10T22:35:40Z", "lastrevid": 1169488539, "length": 19558}, "110083": {"pageid": 110083, "ns": 0, "title": "Claxton, Georgia", "contentmodel": "wikitext", "pagelanguage": "en", "pagelanguagehtmlcode": "en", "pagelanguagedir": "ltr", "touched": "2023-10-10T22:35:40Z", "lastrevid": 1165539625, "length": 20187}, "110318": {"pageid": 110318, "ns": 0, "title": "Clayton, Georgia", "contentmodel": "wikitext", "pagelanguage": "en", "pagelanguagehtmlcode": "en", "pagelanguagedir": "ltr", "touched": "2023-10-10T22:35:41Z", "lastrevid": 1165644186, "length": 17385}, "110156": {"pageid": 110156, "ns": 0, "title": "Clermont, Georgia", "contentmodel": "wikitext", "pagelanguage": "en", "pagelanguagehtmlcode": "en", "pagelanguagedir": "ltr", "touched": "2023-10-10T22:35:40Z", "lastrevid": 1166018167, "length": 10002}, "110434": {"pageid": 110434, "ns": 0, "title": "Cleveland, Georgia", "contentmodel": "wikitext", "pagelanguage": "en", "pagelanguagehtmlcode": "en", "pagelanguagedir": "ltr", "touched": "2023-10-10T22:35:41Z", "lastrevid": 1173580782, "length": 17028}}}}