{"batchcomplete": "", "query": {"normalized": [{"from": "Pioneer Village, Kentucky ", "to": "Pioneer Village, Kentucky"}, {"from": " Pippa Passes, Kentucky ", "to": "Pippa Passes, Kentucky"}, {"from": " Plantation, Kentucky ", "to": "Plantation, Kentucky"}, {"from": " Pleasureville, Kentucky ", "to": "Pleasureville, Kentucky"}, {"from": " Plum Springs, Kentucky ", "to": "Plum Springs, Kentucky"}, {"from": " Poplar Hills, Kentucky ", "to": "Poplar Hills, Kentucky"}, {"from": " Powderly, Kentucky ", "to": "Powderly, Kentucky"}, {"from": " Prestonsburg, Kentucky ", "to": "Prestonsburg, Kentucky"}, {"from": " Prestonville, Kentucky ", "to": "Prestonville, Kentucky"}, {"from": " Princeton, Kentucky ", "to": "Princeton, Kentucky"}, {"from": " Prospect, Kentucky ", "to": "Prospect, Kentucky"}, {"from": " Providence, Kentucky ", "to": "Providence, Kentucky"}, {"from": " Raceland, Kentucky ", "to": "Raceland, Kentucky"}, {"from": " Radcliff, Kentucky ", "to": "Radcliff, Kentucky"}, {"from": " Ravenna, Kentucky ", "to": "Ravenna, Kentucky"}, {"from": " Raywick, Kentucky ", "to": "Raywick, Kentucky"}, {"from": " Richlawn, Kentucky ", "to": "Richlawn, Kentucky"}, {"from": " Richmond, Kentucky ", "to": "Richmond, Kentucky"}, {"from": " River Bluff, Kentucky ", "to": "River Bluff, Kentucky"}, {"from": " Riverwood, Kentucky ", "to": "Riverwood, Kentucky"}, {"from": " Robards, Kentucky ", "to": "Robards, Kentucky"}, {"from": " Rochester, Kentucky ", "to": "Rochester, Kentucky"}, {"from": " Rockport, Kentucky ", "to": "Rockport, Kentucky"}, {"from": " Rolling Fields, Kentucky ", "to": "Rolling Fields, Kentucky"}, {"from": " Rolling Hills, Kentucky ", "to": "Rolling Hills, Kentucky"}, {"from": " Russell, Kentucky ", "to": "Russell, Kentucky"}, {"from": " Russell Springs, Kentucky ", "to": "Russell Springs, Kentucky"}, {"from": " Russellville, Kentucky ", "to": "Russellville, Kentucky"}, {"from": " Ryland Heights, Kentucky ", "to": "Ryland Heights, Kentucky"}, {"from": " Sacramento, Kentucky ", "to": "Sacramento, Kentucky"}, {"from": " Sadieville, Kentucky ", "to": "Sadieville, Kentucky"}, {"from": " St. Charles, Kentucky ", "to": "St. Charles, Kentucky"}, {"from": " St. Mary, Kentucky ", "to": "St. Mary, Kentucky"}, {"from": " St. Matthews, Kentucky ", "to": "St. Matthews, Kentucky"}, {"from": " St. Regis Park, Kentucky ", "to": "St. Regis Park, Kentucky"}, {"from": " Salem, Kentucky ", "to": "Salem, Kentucky"}, {"from": " Salt Lick, Kentucky ", "to": "Salt Lick, Kentucky"}, {"from": " Salyersville, Kentucky ", "to": "Salyersville, Kentucky"}, {"from": " Sanders, Kentucky ", "to": "Sanders, Kentucky"}, {"from": " Sandy Hook, Kentucky ", "to": "Sandy Hook, Kentucky"}, {"from": " Sardis, Kentucky ", "to": "Sardis, Kentucky"}, {"from": " Science Hill, Kentucky ", "to": "Science Hill, Kentucky"}, {"from": " Scottsville, Kentucky ", "to": "Scottsville, Kentucky"}, {"from": " Sebree, Kentucky ", "to": "Sebree, Kentucky"}, {"from": " Seneca Gardens, Kentucky ", "to": "Seneca Gardens, Kentucky"}, {"from": " Sharpsburg, Kentucky ", "to": "Sharpsburg, Kentucky"}, {"from": " Shelbyville, Kentucky ", "to": "Shelbyville, Kentucky"}, {"from": " Shepherdsville, Kentucky ", "to": "Shepherdsville, Kentucky"}, {"from": " Shively, Kentucky ", "to": "Shively, Kentucky"}, {"from": " Silver Grove, Kentucky", "to": "Silver Grove, Kentucky"}], "pages": {"115052": {"pageid": 115052, "ns": 0, "title": "Pioneer Village, Kentucky", "contentmodel": "wikitext", "pagelanguage": "en", "pagelanguagehtmlcode": "en", "pagelanguagedir": "ltr", "touched": "2023-10-10T22:35:44Z", "lastrevid": 1165897924, "length": 7867}, "115296": {"pageid": 115296, "ns": 0, "title": "Pippa Passes, Kentucky", "contentmodel": "wikitext", "pagelanguage": "en", "pagelanguagehtmlcode": "en", "pagelanguagedir": "ltr", "touched": "2023-10-10T22:35:44Z", "lastrevid": 1165897963, "length": 10389}, "115239": {"pageid": 115239, "ns": 0, "title": "Plantation, Kentucky", "contentmodel": "wikitext", "pagelanguage": "en", "pagelanguagehtmlcode": "en", "pagelanguagedir": "ltr", "touched": "2023-10-14T07:53:36Z", "lastrevid": 1165898106, "length": 9062}, "150462": {"pageid": 150462, "ns": 0, "title": "Pleasureville, Kentucky", "contentmodel": "wikitext", "pagelanguage": "en", "pagelanguagehtmlcode": "en", "pagelanguagedir": "ltr", "touched": "2023-10-10T22:36:07Z", "lastrevid": 1165898205, "length": 10739}, "115445": {"pageid": 115445, "ns": 0, "title": "Plum Springs, Kentucky", "contentmodel": "wikitext", "pagelanguage": "en", "pagelanguagehtmlcode": "en", "pagelanguagedir": "ltr", "touched": "2023-10-10T22:35:44Z", "lastrevid": 1165898224, "length": 7077}, "115242": {"pageid": 115242, "ns": 0, "title": "Poplar Hills, Kentucky", "contentmodel": "wikitext", "pagelanguage": "en", "pagelanguagehtmlcode": "en", "pagelanguagedir": "ltr", "touched": "2023-10-14T07:53:36Z", "lastrevid": 1165898411, "length": 10003}, "115374": {"pageid": 115374, "ns": 0, "title": "Powderly, Kentucky", "contentmodel": "wikitext", "pagelanguage": "en", "pagelanguagehtmlcode": "en", "pagelanguagedir": "ltr", "touched": "2023-10-10T22:35:44Z", "lastrevid": 1165898600, "length": 9610}, "101179": {"pageid": 101179, "ns": 0, "title": "Prestonsburg, Kentucky", "contentmodel": "wikitext", "pagelanguage": "en", "pagelanguagehtmlcode": "en", "pagelanguagedir": "ltr", "touched": "2023-10-10T22:35:35Z", "lastrevid": 1172406113, "length": 16252}, "115081": {"pageid": 115081, "ns": 0, "title": "Prestonville, Kentucky", "contentmodel": "wikitext", "pagelanguage": "en", "pagelanguagehtmlcode": "en", "pagelanguagedir": "ltr", "touched": "2023-10-10T22:35:44Z", "lastrevid": 1165898754, "length": 7306}, "115058": {"pageid": 115058, "ns": 0, "title": "Princeton, Kentucky", "contentmodel": "wikitext", "pagelanguage": "en", "pagelanguagehtmlcode": "en", "pagelanguagedir": "ltr", "touched": "2023-10-10T22:35:44Z", "lastrevid": 1168614247, "length": 25473}, "150464": {"pageid": 150464, "ns": 0, "title": "Prospect, Kentucky", "contentmodel": "wikitext", "pagelanguage": "en", "pagelanguagehtmlcode": "en", "pagelanguagedir": "ltr", "touched": "2023-10-14T07:53:36Z", "lastrevid": 1165898846, "length": 11017}, "115454": {"pageid": 115454, "ns": 0, "title": "Providence, Kentucky", "contentmodel": "wikitext", "pagelanguage": "en", "pagelanguagehtmlcode": "en", "pagelanguagedir": "ltr", "touched": "2023-10-10T22:35:44Z", "lastrevid": 1165898862, "length": 14154}, "115130": {"pageid": 115130, "ns": 0, "title": "Raceland, Kentucky", "contentmodel": "wikitext", "pagelanguage": "en", "pagelanguagehtmlcode": "en", "pagelanguagedir": "ltr", "touched": "2023-10-10T22:35:44Z", "lastrevid": 1165899051, "length": 10923}, "115138": {"pageid": 115138, "ns": 0, "title": "Radcliff, Kentucky", "contentmodel": "wikitext", "pagelanguage": "en", "pagelanguagehtmlcode": "en", "pagelanguagedir": "ltr", "touched": "2023-10-10T22:35:44Z", "lastrevid": 1165899055, "length": 18482}, "115105": {"pageid": 115105, "ns": 0, "title": "Ravenna, Kentucky", "contentmodel": "wikitext", "pagelanguage": "en", "pagelanguagehtmlcode": "en", "pagelanguagedir": "ltr", "touched": "2023-10-10T22:35:44Z", "lastrevid": 1165899223, "length": 10464}, "115334": {"pageid": 115334, "ns": 0, "title": "Raywick, Kentucky", "contentmodel": "wikitext", "pagelanguage": "en", "pagelanguagehtmlcode": "en", "pagelanguagedir": "ltr", "touched": "2023-10-10T22:35:44Z", "lastrevid": 1165899275, "length": 7232}, "115243": {"pageid": 115243, "ns": 0, "title": "Richlawn, Kentucky", "contentmodel": "wikitext", "pagelanguage": "en", "pagelanguagehtmlcode": "en", "pagelanguagedir": "ltr", "touched": "2023-10-14T07:53:36Z", "lastrevid": 1165899633, "length": 7281}, "115329": {"pageid": 115329, "ns": 0, "title": "Richmond, Kentucky", "contentmodel": "wikitext", "pagelanguage": "en", "pagelanguagehtmlcode": "en", "pagelanguagedir": "ltr", "touched": "2023-10-10T22:35:44Z", "lastrevid": 1165899653, "length": 22020}, "115394": {"pageid": 115394, "ns": 0, "title": "River Bluff, Kentucky", "contentmodel": "wikitext", "pagelanguage": "en", "pagelanguagehtmlcode": "en", "pagelanguagedir": "ltr", "touched": "2023-10-10T22:35:44Z", "lastrevid": 1165899829, "length": 5847}, "115244": {"pageid": 115244, "ns": 0, "title": "Riverwood, Kentucky", "contentmodel": "wikitext", "pagelanguage": "en", "pagelanguagehtmlcode": "en", "pagelanguagedir": "ltr", "touched": "2023-10-14T07:53:36Z", "lastrevid": 1165899871, "length": 7771}, "115156": {"pageid": 115156, "ns": 0, "title": "Robards, Kentucky", "contentmodel": "wikitext", "pagelanguage": "en", "pagelanguagehtmlcode": "en", "pagelanguagedir": "ltr", "touched": "2023-10-10T22:35:44Z", "lastrevid": 1176703210, "length": 10618}, "115055": {"pageid": 115055, "ns": 0, "title": "Rochester, Kentucky", "contentmodel": "wikitext", "pagelanguage": "en", "pagelanguagehtmlcode": "en", "pagelanguagedir": "ltr", "touched": "2023-10-10T22:35:44Z", "lastrevid": 1133257917, "length": 10665}, "115386": {"pageid": 115386, "ns": 0, "title": "Rockport, Kentucky", "contentmodel": "wikitext", "pagelanguage": "en", "pagelanguagehtmlcode": "en", "pagelanguagedir": "ltr", "touched": "2023-10-10T22:35:44Z", "lastrevid": 1169533386, "length": 7137}, "115245": {"pageid": 115245, "ns": 0, "title": "Rolling Fields, Kentucky", "contentmodel": "wikitext", "pagelanguage": "en", "pagelanguagehtmlcode": "en", "pagelanguagedir": "ltr", "touched": "2023-10-14T07:53:36Z", "lastrevid": 1165900120, "length": 8504}, "115246": {"pageid": 115246, "ns": 0, "title": "Rolling Hills, Kentucky", "contentmodel": "wikitext", "pagelanguage": "en", "pagelanguagehtmlcode": "en", "pagelanguagedir": "ltr", "touched": "2023-10-14T07:53:36Z", "lastrevid": 1165900129, "length": 7147}, "115131": {"pageid": 115131, "ns": 0, "title": "Russell, Kentucky", "contentmodel": "wikitext", "pagelanguage": "en", "pagelanguagehtmlcode": "en", "pagelanguagedir": "ltr", "touched": "2023-10-10T22:35:44Z", "lastrevid": 1177229785, "length": 16699}, "115422": {"pageid": 115422, "ns": 0, "title": "Russell Springs, Kentucky", "contentmodel": "wikitext", "pagelanguage": "en", "pagelanguagehtmlcode": "en", "pagelanguagedir": "ltr", "touched": "2023-10-10T22:35:44Z", "lastrevid": 1165900480, "length": 9968}, "115325": {"pageid": 115325, "ns": 0, "title": "Russellville, Kentucky", "contentmodel": "wikitext", "pagelanguage": "en", "pagelanguagehtmlcode": "en", "pagelanguagedir": "ltr", "touched": "2023-10-10T22:35:44Z", "lastrevid": 1165900507, "length": 17539}, "115291": {"pageid": 115291, "ns": 0, "title": "Ryland Heights, Kentucky", "contentmodel": "wikitext", "pagelanguage": "en", "pagelanguagehtmlcode": "en", "pagelanguagedir": "ltr", "touched": "2023-10-10T22:35:44Z", "lastrevid": 1176318869, "length": 7302}, "115355": {"pageid": 115355, "ns": 0, "title": "Sacramento, Kentucky", "contentmodel": "wikitext", "pagelanguage": "en", "pagelanguagehtmlcode": "en", "pagelanguagedir": "ltr", "touched": "2023-10-10T22:35:44Z", "lastrevid": 1165900582, "length": 9466}, "115424": {"pageid": 115424, "ns": 0, "title": "Sadieville, Kentucky", "contentmodel": "wikitext", "pagelanguage": "en", "pagelanguagehtmlcode": "en", "pagelanguagedir": "ltr", "touched": "2023-10-10T22:35:44Z", "lastrevid": 1172923984, "length": 7598}, "115320": {"pageid": 115320, "ns": 0, "title": "Salem, Kentucky", "contentmodel": "wikitext", "pagelanguage": "en", "pagelanguagehtmlcode": "en", "pagelanguagedir": "ltr", "touched": "2023-10-10T22:35:44Z", "lastrevid": 1178929929, "length": 7703}, "115023": {"pageid": 115023, "ns": 0, "title": "Salt Lick, Kentucky", "contentmodel": "wikitext", "pagelanguage": "en", "pagelanguagehtmlcode": "en", "pagelanguagedir": "ltr", "touched": "2023-10-10T22:35:44Z", "lastrevid": 1165900674, "length": 8715}, "115330": {"pageid": 115330, "ns": 0, "title": "Salyersville, Kentucky", "contentmodel": "wikitext", "pagelanguage": "en", "pagelanguagehtmlcode": "en", "pagelanguagedir": "ltr", "touched": "2023-10-10T22:35:44Z", "lastrevid": 1159099471, "length": 24384}, "115082": {"pageid": 115082, "ns": 0, "title": "Sanders, Kentucky", "contentmodel": "wikitext", "pagelanguage": "en", "pagelanguagehtmlcode": "en", "pagelanguagedir": "ltr", "touched": "2023-10-10T22:35:44Z", "lastrevid": 1165900781, "length": 8194}, "115103": {"pageid": 115103, "ns": 0, "title": "Sandy Hook, Kentucky", "contentmodel": "wikitext", "pagelanguage": "en", "pagelanguagehtmlcode": "en", "pagelanguagedir": "ltr", "touched": "2023-10-10T22:35:44Z", "lastrevid": 1165900802, "length": 10100}, "115342": {"pageid": 115342, "ns": 0, "title": "Sardis, Kentucky", "contentmodel": "wikitext", "pagelanguage": "en", "pagelanguagehtmlcode": "en", "pagelanguagedir": "ltr", "touched": "2023-10-10T22:35:44Z", "lastrevid": 1165900899, "length": 7066}, "115413": {"pageid": 115413, "ns": 0, "title": "Science Hill, Kentucky", "contentmodel": "wikitext", "pagelanguage": "en", "pagelanguagehtmlcode": "en", "pagelanguagedir": "ltr", "touched": "2023-10-10T22:35:44Z", "lastrevid": 1165900994, "length": 8179}, "115011": {"pageid": 115011, "ns": 0, "title": "Scottsville, Kentucky", "contentmodel": "wikitext", "pagelanguage": "en", "pagelanguagehtmlcode": "en", "pagelanguagedir": "ltr", "touched": "2023-10-16T15:40:36Z", "lastrevid": 1180425473, "length": 12621}, "115455": {"pageid": 115455, "ns": 0, "title": "Sebree, Kentucky", "contentmodel": "wikitext", "pagelanguage": "en", "pagelanguagehtmlcode": "en", "pagelanguagedir": "ltr", "touched": "2023-10-10T22:35:44Z", "lastrevid": 1165901148, "length": 10755}, "115247": {"pageid": 115247, "ns": 0, "title": "Seneca Gardens, Kentucky", "contentmodel": "wikitext", "pagelanguage": "en", "pagelanguagehtmlcode": "en", "pagelanguagedir": "ltr", "touched": "2023-10-14T07:53:36Z", "lastrevid": 1165901249, "length": 13252}, "115024": {"pageid": 115024, "ns": 0, "title": "Sharpsburg, Kentucky", "contentmodel": "wikitext", "pagelanguage": "en", "pagelanguagehtmlcode": "en", "pagelanguagedir": "ltr", "touched": "2023-10-10T22:35:44Z", "lastrevid": 1165901435, "length": 8380}, "115426": {"pageid": 115426, "ns": 0, "title": "Shelbyville, Kentucky", "contentmodel": "wikitext", "pagelanguage": "en", "pagelanguagehtmlcode": "en", "pagelanguagedir": "ltr", "touched": "2023-10-14T07:53:36Z", "lastrevid": 1177596638, "length": 22504}, "115053": {"pageid": 115053, "ns": 0, "title": "Shepherdsville, Kentucky", "contentmodel": "wikitext", "pagelanguage": "en", "pagelanguagehtmlcode": "en", "pagelanguagedir": "ltr", "touched": "2023-10-14T07:53:36Z", "lastrevid": 1165869643, "length": 15856}, "115248": {"pageid": 115248, "ns": 0, "title": "Shively, Kentucky", "contentmodel": "wikitext", "pagelanguage": "en", "pagelanguagehtmlcode": "en", "pagelanguagedir": "ltr", "touched": "2023-10-14T07:53:36Z", "lastrevid": 1165901661, "length": 18838}, "115073": {"pageid": 115073, "ns": 0, "title": "Silver Grove, Kentucky", "contentmodel": "wikitext", "pagelanguage": "en", "pagelanguagehtmlcode": "en", "pagelanguagedir": "ltr", "touched": "2023-10-10T22:35:44Z", "lastrevid": 1176469269, "length": 9647}, "115169": {"pageid": 115169, "ns": 0, "title": "St. Charles, Kentucky", "contentmodel": "wikitext", "pagelanguage": "en", "pagelanguagehtmlcode": "en", "pagelanguagedir": "ltr", "touched": "2023-10-10T22:35:44Z", "lastrevid": 1165902825, "length": 7857}, "40704679": {"pageid": 40704679, "ns": 0, "title": "St. Mary, Kentucky", "contentmodel": "wikitext", "pagelanguage": "en", "pagelanguagehtmlcode": "en", "pagelanguagedir": "ltr", "touched": "2023-10-10T23:14:04Z", "lastrevid": 1153161434, "length": 8791}, "115254": {"pageid": 115254, "ns": 0, "title": "St. Matthews, Kentucky", "contentmodel": "wikitext", "pagelanguage": "en", "pagelanguagehtmlcode": "en", "pagelanguagedir": "ltr", "touched": "2023-10-14T07:53:36Z", "lastrevid": 1165679659, "length": 18755}, "115255": {"pageid": 115255, "ns": 0, "title": "St. Regis Park, Kentucky", "contentmodel": "wikitext", "pagelanguage": "en", "pagelanguagehtmlcode": "en", "pagelanguagedir": "ltr", "touched": "2023-10-14T07:53:36Z", "lastrevid": 1165902970, "length": 7827}}}}